[{"category":"electronics","inventory":10,"rating":3.8,"currency":"INR","price":2500.0,"origin":"Asia","product":"XTP mobile","arrival":null,"discount":{"amount":"0","discountTag":"No discounts"}},{"category":"electronics","inventory":5,"rating":1.8,"currency":"INR","price":4500.0,"origin":"Asia","product":"Maximize mobile","arrival":null,"discount":{"amount":"0","discountTag":"No discounts"}},{"category":"clothing","inventory":50,"rating":4.8,"currency":"INR","price":1800.0,"origin":"Asia","product":"Jeet white shoes","arrival":null,"discount":{"amount":"0","discountTag":"No discounts"}},{"category":"grooming","inventory":10,"rating":2.0,"currency":"INR","price":150.0,"origin":"Europe","product":"Pearly tooth brush","arrival":null,"discount":{"amount":"0","discountTag":"No discounts"}},{"category":"accessories","inventory":10,"rating":0.0,"currency":"INR","price":2199.0,"origin":"America","product":"BOA power bank","arrival":"NEW","discount":{"amount":"0","discountTag":"No discounts"}},{"category":"toys","inventory":10,"rating":2.8,"currency":"INR","price":4049.3801,"origin":"Asia","product":"remote control car","arrival":null,"discount":{"amount":"0","discountTag":"No discounts"}},{"category":"books","inventory":5,"rating":4.8,"currency":"INR","price":3547.8044,"origin":"America","product":"Zen and The art of motorcycle maintenance","arrival":null,"discount":{"amount":"0","discountTag":"No discounts"}},{"category":"apparels","inventory":10,"rating":4.2,"currency":"INR","price":2100.5205,"origin":"Africa","product":"hawaiian shirts","arrival":null,"discount":{"amount":"0","discountTag":"No discounts"}},{"category":"home","inventory":30,"rating":4.2,"currency":"INR","price":490.0,"origin":"Africa","product":"water bottle","arrival":null,"discount":{"amount":"0","discountTag":"No discounts"}},{"category":"accessories","inventory":10,"rating":3.2,"currency":"INR","price":190.0,"origin":"Asia","product":"iron man mousepad","arrival":null,"discount":{"amount":"0","discountTag":"No discounts"}},{"category":"furnishing","inventory":45,"rating":3.2,"currency":"INR","price":190.0,"origin":"Asia","product":"lunch box","arrival":null,"discount":{"amount":"0","discountTag":"No discounts"}}]